filfla/__init__.py
filfla/ffl.py
filfla_karjakak-0.1.8.dist-info/METADATA
filfla_karjakak-0.1.8.dist-info/WHEEL
filfla_karjakak-0.1.8.dist-info/entry_points.txt
filfla_karjakak-0.1.8.dist-info/top_level.txt
filfla_karjakak-0.1.8.dist-info/RECORD
