Metadata-Version: 2.1
Name: filfla-karjakak
Version: 0.1.8
Summary: File or Folder, for flag view and changer.
Home-page: https://github.com/kakkarja/FileFlag
Author: karjakak
Author-email: kakkarja.github@gmail.com
License: BSD3 License
Platform: UNKNOWN
Classifier: Environment :: MacOS X
Classifier: Programming Language :: Python :: 3.10
Classifier: License :: OSI Approved :: BSD License
Requires-Python: >=3.10
Requires-Dist: excptr-karjakak (>=0.1.1)
